uc/__init__.py
uc/authUC.py
uc/getAccounts.py
uc/getAssetClassById.py
uc/getAssetClasses.py
uc/getAssets.py
uc/getAssetsById.py
uc/getListDef.py
uc/getLogins.py
uc/getUser.py
uc/getUserApiKey.py
uc/getWfClasses.py
uc/getWfFeilds.py
uc/getWfReports.py
uc/getWoById.py
uc/getWorkOrders.py
uc/postAsset.py
uc/postAssetDelete.py
uc/postCloseWo.py
uc/postSubmitWork.py
uc/postWfFields.py
uc/postWo.py
uc/helpers/__init__.py
uc/helpers/helpers.py
utilitycloud-0.0.3.dist-info/LICENSE
utilitycloud-0.0.3.dist-info/METADATA
utilitycloud-0.0.3.dist-info/WHEEL
utilitycloud-0.0.3.dist-info/top_level.txt
utilitycloud-0.0.3.dist-info/RECORD
