Metadata-Version: 2.1
Name: utilitycloud
Version: 0.0.3
Summary: Utility Cloud Python Library
Author-email: Andy Crawford <andy.crawford@utilitycloud.us>, Romario Jashari <romario.jashari@utilitycloud.us>
License: Copyright (c) 2022 Utility Cloud Inc.        
Project-URL: Homepage, https://bitbucket.org/romariojashari/uc/src/master/
Project-URL: Bug Tracker, https://bitbucket.org/romariojashari/uc/src/master/
Classifier: Programming Language :: Python :: 3
Classifier: License :: OSI Approved :: MIT License
Classifier: Operating System :: OS Independent
Requires-Python: >=3.7
License-File: LICENSE
